sif_tools/CONVERT.py
sif_tools/SIFopen.py
sif_tools/SPECTRAL.py
sif_tools/__init__.py
sif_tools/calibration.py
sif_tools/conversion.py
sif_tools/parser.py
sif_tools/source.py
sif_tools/utils.py
sif_tools-2.1.2.dist-info/LICENSE
sif_tools-2.1.2.dist-info/METADATA
sif_tools-2.1.2.dist-info/WHEEL
sif_tools-2.1.2.dist-info/entry_points.txt
sif_tools-2.1.2.dist-info/top_level.txt
sif_tools-2.1.2.dist-info/RECORD
