Metadata-Version: 2.1
Name: sif_tools
Version: 2.1.2
Summary: A light-weight package for SIF file conversion
Home-page: https://github.com/BjornFS/SIF-Tools
Author: Bjorn F. Schroder Nielsen
Author-email: Bjorn@SchroderNielsen.com
Classifier: Programming Language :: Python :: 3
Classifier: License :: OSI Approved :: Mozilla Public License 2.0 (MPL 2.0)
Classifier: Operating System :: OS Independent
Requires-Python: >=3.6
License-File: LICENSE
Requires-Dist: numpy
